jataruku/__init__.py
jataruku-0.1.1.dist-info/LICENSE
jataruku-0.1.1.dist-info/METADATA
jataruku-0.1.1.dist-info/WHEEL
jataruku-0.1.1.dist-info/top_level.txt
jataruku-0.1.1.dist-info/RECORD
