Metadata-Version: 2.1
Name: jataruku
Version: 0.1.1
Summary: A PID controller written in Python3
Home-page: https://github.com/deniz195/jataruku
Author: Deniz Bozyigit
Author-email: deniz195@gmail.com
License: Copyright &copy; 2013, Jeremy Bornstein
